collect4easyplot/__init__.py
collect4easyplot/data_grabber.py
collect4easyplot-0.14.dist-info/METADATA
collect4easyplot-0.14.dist-info/WHEEL
collect4easyplot-0.14.dist-info/top_level.txt
collect4easyplot-0.14.dist-info/RECORD
