Metadata-Version: 2.1
Name: collect4easyplot
Version: 0.14
Summary: A complementary library for using EasyPlot with Python
Home-page: https://github.com/RaichelgauzGuy/Collect4EasyPlot
Author: Guy Raichelgauz
Author-email: guy.raichelgauz@gmail.com
